django_initials_avatar/__init__.py
django_initials_avatar/admin.py
django_initials_avatar/app_settings.py
django_initials_avatar/apps.py
django_initials_avatar/models.py
django_initials_avatar/tests.py
django_initials_avatar/urls.py
django_initials_avatar/views.py
django_initials_avatar/migrations/__init__.py
django_initials_avatar/templatetags/__init__.py
django_initials_avatar/templatetags/initials_avatar.py
django_initials_avatar/utils/__init__.py
django_initials_avatar/utils/svg_avatar.py
django_initials_avatar-0.0.7.dist-info/LICENSE
django_initials_avatar-0.0.7.dist-info/METADATA
django_initials_avatar-0.0.7.dist-info/WHEEL
django_initials_avatar-0.0.7.dist-info/top_level.txt
django_initials_avatar-0.0.7.dist-info/RECORD
