Metadata-Version: 2.1
Name: django_initials_avatar
Version: 0.0.7
Summary: A ridiculously simple avatar generator with initials from names.
Home-page: https://github.com/riquedev/django-initials-avatar
Author: Henrique da Silva Santos
Author-email: henrique.santos@4u360.com.br
License: Apache License 2.0
Project-URL: Bug Tracker, https://github.com/riquedev/django-initials-avatar/issues
Project-URL: Repository, https://github.com/riquedev/django-initials-avatar
Keywords: letter,initials,avatar,django
Classifier: Framework :: Django
Classifier: Development Status :: 4 - Beta
Classifier: Intended Audience :: Developers
Classifier: Programming Language :: Python :: 3
Requires-Python: >=3.6
License-File: LICENSE
Requires-Dist: Django >=3.2.14
